[
  {
    "id": "aria-allowed-attr",
    "title": "`[aria-*]` attributes do not match their roles",
    "description": "Each ARIA `role` supports a specific subset of `aria-*` attributes. Mismatching these invalidates the `aria-*` attributes. [Learn more](https://web.dev/aria-allowed-attr/).",
    "score": 0,
    "scoreDisplayMode": "binary",
    "details": {
      "type": "table",
      "headings": [
        {
          "key": "node",
          "itemType": "node",
          "subItemsHeading": {
            "key": "relatedNode",
            "itemType": "node"
          },
          "text": "Failing Elements"
        }
      ],
      "items": [
        {
          "node": {
            "type": "node",
            "lhId": "9-510-SPAN",
            "path": "1,HTML,1,BODY,7,HEADER,1,NAV,0,DIV,1,DIV,1,UL,0,LI,1,SPAN",
            "selector": "div.left-panel-top-2 > ul.usa-nav__primary > li.usa-nav__primary-item > span.nav-toggle",
            "boundingRect": {
              "top": 144,
              "bottom": 160,
              "left": 253,
              "right": 265,
              "width": 11,
              "height": 16
            },
            "snippet": "<span class=\"nav-toggle\" tabindex=\"0\" aria-expanded=\"false\">",
            "nodeLabel": "Toggle submenu",
            "explanation": "Fix any of the following:\n  ARIA attribute is not allowed: aria-expanded=\"false\""
          }
        },
        {
          "node": {
            "type": "node",
            "lhId": "9-511-SPAN",
            "path": "1,HTML,1,BODY,7,HEADER,1,NAV,0,DIV,1,DIV,1,UL,1,LI,1,SPAN",
            "selector": "div.left-panel-top-2 > ul.usa-nav__primary > li.usa-nav__primary-item > span.nav-toggle",
            "boundingRect": {
              "top": 144,
              "bottom": 160,
              "left": 359,
              "right": 371,
              "width": 11,
              "height": 16
            },
            "snippet": "<span class=\"nav-toggle\" tabindex=\"0\" aria-expanded=\"false\">",
            "nodeLabel": "Toggle submenu",
            "explanation": "Fix any of the following:\n  ARIA attribute is not allowed: aria-expanded=\"false\""
          }
        },
        {
          "node": {
            "type": "node",
            "lhId": "9-512-SPAN",
            "path": "1,HTML,1,BODY,7,HEADER,1,NAV,0,DIV,1,DIV,1,UL,2,LI,1,SPAN",
            "selector": "div.left-panel-top-2 > ul.usa-nav__primary > li.usa-nav__primary-item > span.nav-toggle",
            "boundingRect": {
              "top": 144,
              "bottom": 160,
              "left": 494,
              "right": 506,
              "width": 11,
              "height": 16
            },
            "snippet": "<span class=\"nav-toggle\" tabindex=\"0\" aria-expanded=\"false\">",
            "nodeLabel": "Toggle submenu",
            "explanation": "Fix any of the following:\n  ARIA attribute is not allowed: aria-expanded=\"false\""
          }
        },
        {
          "node": {
            "type": "node",
            "lhId": "9-513-SPAN",
            "path": "1,HTML,1,BODY,7,HEADER,1,NAV,0,DIV,1,DIV,1,UL,3,LI,1,SPAN",
            "selector": "div.left-panel-top-2 > ul.usa-nav__primary > li.usa-nav__primary-item > span.nav-toggle",
            "boundingRect": {
              "top": 144,
              "bottom": 160,
              "left": 640,
              "right": 652,
              "width": 11,
              "height": 16
            },
            "snippet": "<span class=\"nav-toggle\" tabindex=\"0\" aria-expanded=\"false\">",
            "nodeLabel": "Toggle submenu",
            "explanation": "Fix any of the following:\n  ARIA attribute is not allowed: aria-expanded=\"false\""
          }
        },
        {
          "node": {
            "type": "node",
            "lhId": "9-514-SPAN",
            "path": "1,HTML,1,BODY,7,HEADER,1,NAV,0,DIV,1,DIV,1,UL,4,LI,1,SPAN",
            "selector": "div.left-panel-top-2 > ul.usa-nav__primary > li.usa-nav__primary-item > span.nav-toggle",
            "boundingRect": {
              "top": 144,
              "bottom": 160,
              "left": 780,
              "right": 792,
              "width": 11,
              "height": 16
            },
            "snippet": "<span class=\"nav-toggle\" tabindex=\"0\" aria-expanded=\"false\">",
            "nodeLabel": "Toggle submenu",
            "explanation": "Fix any of the following:\n  ARIA attribute is not allowed: aria-expanded=\"false\""
          }
        },
        {
          "node": {
            "type": "node",
            "lhId": "9-515-SPAN",
            "path": "1,HTML,1,BODY,7,HEADER,1,NAV,0,DIV,1,DIV,1,UL,5,LI,1,SPAN",
            "selector": "div.left-panel-top-2 > ul.usa-nav__primary > li.usa-nav__primary-item > span.nav-toggle",
            "boundingRect": {
              "top": 144,
              "bottom": 160,
              "left": 967,
              "right": 979,
              "width": 11,
              "height": 16
            },
            "snippet": "<span class=\"nav-toggle\" tabindex=\"0\" aria-expanded=\"false\">",
            "nodeLabel": "Toggle submenu",
            "explanation": "Fix any of the following:\n  ARIA attribute is not allowed: aria-expanded=\"false\""
          }
        },
        {
          "node": {
            "type": "node",
            "lhId": "9-516-DIV",
            "path": "1,HTML,1,BODY,10,MAIN,1,DIV,0,DIV,3,DIV,1,SECTION,0,DIV,1,DIV,6,DIV,1,SECTION,0,DIV,1,DIV,2,DIV,2,DIV",
            "selector": "div.grid-container > div > div.grid-col-12 > div.usa-accordion",
            "boundingRect": {
              "top": 848,
              "bottom": 928,
              "left": 451,
              "right": 1091,
              "width": 640,
              "height": 80
            },
            "snippet": "<div class=\"usa-accordion usa-accordion--bordered\" aria-multiselectable=\"true\">",
            "nodeLabel": "I left my government job before becoming eligible for retirement. What are my o…",
            "explanation": "Fix any of the following:\n  ARIA attribute is not allowed: aria-multiselectable=\"true\""
          }
        },
        {
          "node": {
            "type": "node",
            "lhId": "9-517-DIV",
            "path": "1,HTML,1,BODY,10,MAIN,1,DIV,0,DIV,3,DIV,1,SECTION,0,DIV,1,DIV,6,DIV,1,SECTION,0,DIV,1,DIV,2,DIV,3,DIV",
            "selector": "div.grid-container > div > div.grid-col-12 > div.usa-accordion",
            "boundingRect": {
              "top": 944,
              "bottom": 1024,
              "left": 451,
              "right": 1091,
              "width": 640,
              "height": 80
            },
            "snippet": "<div class=\"usa-accordion usa-accordion--bordered\" aria-multiselectable=\"true\">",
            "nodeLabel": "How do I apply to have my retirement contributions returned to me in a lump sum…",
            "explanation": "Fix any of the following:\n  ARIA attribute is not allowed: aria-multiselectable=\"true\""
          }
        },
        {
          "node": {
            "type": "node",
            "lhId": "9-518-DIV",
            "path": "1,HTML,1,BODY,10,MAIN,1,DIV,0,DIV,3,DIV,1,SECTION,0,DIV,1,DIV,6,DIV,1,SECTION,0,DIV,1,DIV,2,DIV,4,DIV",
            "selector": "div.grid-container > div > div.grid-col-12 > div.usa-accordion",
            "boundingRect": {
              "top": 1040,
              "bottom": 1096,
              "left": 451,
              "right": 1091,
              "width": 640,
              "height": 56
            },
            "snippet": "<div class=\"usa-accordion usa-accordion--bordered\" aria-multiselectable=\"true\">",
            "nodeLabel": "Will I receive interest on the refund of my retirement deductions?",
            "explanation": "Fix any of the following:\n  ARIA attribute is not allowed: aria-multiselectable=\"true\""
          }
        },
        {
          "node": {
            "type": "node",
            "lhId": "9-519-DIV",
            "path": "1,HTML,1,BODY,10,MAIN,1,DIV,0,DIV,3,DIV,1,SECTION,0,DIV,1,DIV,6,DIV,1,SECTION,0,DIV,1,DIV,2,DIV,5,DIV",
            "selector": "div.grid-container > div > div.grid-col-12 > div.usa-accordion",
            "boundingRect": {
              "top": 1112,
              "bottom": 1168,
              "left": 451,
              "right": 1091,
              "width": 640,
              "height": 56
            },
            "snippet": "<div class=\"usa-accordion usa-accordion--bordered\" aria-multiselectable=\"true\">",
            "nodeLabel": "Is my refund of retirement contributions taxable?",
            "explanation": "Fix any of the following:\n  ARIA attribute is not allowed: aria-multiselectable=\"true\""
          }
        },
        {
          "node": {
            "type": "node",
            "lhId": "9-520-DIV",
            "path": "1,HTML,1,BODY,10,MAIN,1,DIV,0,DIV,3,DIV,1,SECTION,0,DIV,1,DIV,6,DIV,1,SECTION,0,DIV,1,DIV,2,DIV,6,DIV",
            "selector": "div.grid-container > div > div.grid-col-12 > div.usa-accordion",
            "boundingRect": {
              "top": 1184,
              "bottom": 1240,
              "left": 451,
              "right": 1091,
              "width": 640,
              "height": 56
            },
            "snippet": "<div class=\"usa-accordion usa-accordion--bordered\" aria-multiselectable=\"true\">",
            "nodeLabel": "Can I roll over my refund of retirement contributions?",
            "explanation": "Fix any of the following:\n  ARIA attribute is not allowed: aria-multiselectable=\"true\""
          }
        },
        {
          "node": {
            "type": "node",
            "lhId": "9-521-DIV",
            "path": "1,HTML,1,BODY,10,MAIN,1,DIV,0,DIV,3,DIV,1,SECTION,0,DIV,1,DIV,6,DIV,1,SECTION,0,DIV,1,DIV,2,DIV,7,DIV",
            "selector": "div.grid-container > div > div.grid-col-12 > div.usa-accordion",
            "boundingRect": {
              "top": 1256,
              "bottom": 1336,
              "left": 451,
              "right": 1091,
              "width": 640,
              "height": 80
            },
            "snippet": "<div class=\"usa-accordion usa-accordion--bordered\" aria-multiselectable=\"true\">",
            "nodeLabel": "Will I be eligible for health and life insurance benefits when I begin receivin…",
            "explanation": "Fix any of the following:\n  ARIA attribute is not allowed: aria-multiselectable=\"true\""
          }
        },
        {
          "node": {
            "type": "node",
            "lhId": "9-522-DIV",
            "path": "1,HTML,1,BODY,10,MAIN,1,DIV,0,DIV,3,DIV,1,SECTION,0,DIV,1,DIV,6,DIV,1,SECTION,0,DIV,1,DIV,2,DIV,8,DIV",
            "selector": "div.grid-container > div > div.grid-col-12 > div.usa-accordion",
            "boundingRect": {
              "top": 1352,
              "bottom": 1432,
              "left": 451,
              "right": 1091,
              "width": 640,
              "height": 80
            },
            "snippet": "<div class=\"usa-accordion usa-accordion--bordered\" aria-multiselectable=\"true\">",
            "nodeLabel": "How do I report a technical problem with the opm.gov website or with Retirement…",
            "explanation": "Fix any of the following:\n  ARIA attribute is not allowed: aria-multiselectable=\"true\""
          }
        },
        {
          "node": {
            "type": "node",
            "lhId": "9-523-DIV",
            "path": "1,HTML,1,BODY,10,MAIN,1,DIV,0,DIV,3,DIV,1,SECTION,0,DIV,1,DIV,6,DIV,1,SECTION,0,DIV,1,DIV,2,DIV,9,DIV",
            "selector": "div.grid-container > div > div.grid-col-12 > div.usa-accordion",
            "boundingRect": {
              "top": 1448,
              "bottom": 1504,
              "left": 451,
              "right": 1091,
              "width": 640,
              "height": 56
            },
            "snippet": "<div class=\"usa-accordion usa-accordion--bordered\" aria-multiselectable=\"true\">",
            "nodeLabel": "What is Phased Retirement?",
            "explanation": "Fix any of the following:\n  ARIA attribute is not allowed: aria-multiselectable=\"true\""
          }
        },
        {
          "node": {
            "type": "node",
            "lhId": "9-524-DIV",
            "path": "1,HTML,1,BODY,10,MAIN,1,DIV,0,DIV,3,DIV,1,SECTION,0,DIV,1,DIV,6,DIV,1,SECTION,0,DIV,1,DIV,2,DIV,10,DIV",
            "selector": "div.grid-container > div > div.grid-col-12 > div.usa-accordion",
            "boundingRect": {
              "top": 1520,
              "bottom": 1624,
              "left": 451,
              "right": 1091,
              "width": 640,
              "height": 104
            },
            "snippet": "<div class=\"usa-accordion usa-accordion--bordered\" aria-multiselectable=\"true\">",
            "nodeLabel": "Can a spouse that is about to retire transfer or give their spouse their unused…",
            "explanation": "Fix any of the following:\n  ARIA attribute is not allowed: aria-multiselectable=\"true\""
          }
        },
        {
          "node": {
            "type": "node",
            "lhId": "9-525-DIV",
            "path": "1,HTML,1,BODY,10,MAIN,1,DIV,0,DIV,3,DIV,1,SECTION,0,DIV,1,DIV,6,DIV,1,SECTION,0,DIV,1,DIV,2,DIV,11,DIV",
            "selector": "div.grid-container > div > div.grid-col-12 > div.usa-accordion",
            "boundingRect": {
              "top": 1640,
              "bottom": 1720,
              "left": 451,
              "right": 1091,
              "width": 640,
              "height": 80
            },
            "snippet": "<div class=\"usa-accordion usa-accordion--bordered\" aria-multiselectable=\"true\">",
            "nodeLabel": "Can the employee’s five-year enrollment requirements for continuing health insu…",
            "explanation": "Fix any of the following:\n  ARIA attribute is not allowed: aria-multiselectable=\"true\""
          }
        }
      ],
      "debugData": {
        "type": "debugdata",
        "impact": "critical",
        "tags": [
          "cat.aria",
          "wcag2a",
          "wcag412"
        ]
      }
    },
    "errorCount": 16
  },
  {
    "id": "aria-valid-attr-value",
    "title": "`[aria-*]` attributes do not have valid values",
    "description": "Assistive technologies, like screen readers, can't interpret ARIA attributes with invalid values. [Learn more](https://web.dev/aria-valid-attr-value/).",
    "score": 0,
    "scoreDisplayMode": "binary",
    "details": {
      "type": "table",
      "headings": [
        {
          "key": "node",
          "itemType": "node",
          "subItemsHeading": {
            "key": "relatedNode",
            "itemType": "node"
          },
          "text": "Failing Elements"
        }
      ],
      "items": [
        {
          "node": {
            "type": "node",
            "lhId": "9-94-A",
            "path": "1,HTML,1,BODY,7,HEADER,1,NAV,0,DIV,1,DIV,1,UL,5,LI,0,A",
            "selector": "div.left-panel-top-2 > ul.usa-nav__primary > li.usa-nav__primary-item > a",
            "boundingRect": {
              "top": 126,
              "bottom": 178,
              "left": 830,
              "right": 963,
              "width": 133,
              "height": 52
            },
            "snippet": "<a tabindex=\"0\" class=\"\" aria-controls=\"agency services-control-id\" href=\"/services-for-agencies/\">",
            "nodeLabel": "Agency Services",
            "explanation": "Fix all of the following:\n  Invalid ARIA attribute value: aria-controls=\"agency services-control-id\""
          }
        },
        {
          "node": {
            "type": "node",
            "lhId": "9-109-A",
            "path": "1,HTML,1,BODY,7,HEADER,1,NAV,0,DIV,1,DIV,1,UL,6,LI,0,A",
            "selector": "div.left-panel-top-2 > ul.usa-nav__primary > li.usa-nav__primary-item > a",
            "boundingRect": {
              "top": 126,
              "bottom": 178,
              "left": 1017,
              "right": 1156,
              "width": 139,
              "height": 52
            },
            "snippet": "<a tabindex=\"0\" class=\"\" aria-controls=\"operating status-control-id\" href=\"/policy-data-oversight/snow-dismissal-procedures/current-status/\">",
            "nodeLabel": "Operating Status",
            "explanation": "Fix all of the following:\n  Invalid ARIA attribute value: aria-controls=\"operating status-control-id\""
          }
        }
      ],
      "debugData": {
        "type": "debugdata",
        "impact": "critical",
        "tags": [
          "cat.aria",
          "wcag2a",
          "wcag412"
        ]
      }
    },
    "errorCount": 2
  },
  {
    "id": "heading-order",
    "title": "Heading elements are not in a sequentially-descending order",
    "description": "Properly ordered headings that do not skip levels convey the semantic structure of the page, making it easier to navigate and understand when using assistive technologies. [Learn more](https://web.dev/heading-order/).",
    "score": 0,
    "scoreDisplayMode": "binary",
    "details": {
      "type": "table",
      "headings": [
        {
          "key": "node",
          "itemType": "node",
          "subItemsHeading": {
            "key": "relatedNode",
            "itemType": "node"
          },
          "text": "Failing Elements"
        }
      ],
      "items": [
        {
          "node": {
            "type": "node",
            "lhId": "9-526-H3",
            "path": "1,HTML,1,BODY,10,MAIN,1,DIV,0,DIV,3,DIV,1,SECTION,0,DIV,1,DIV,6,DIV,1,SECTION,0,DIV,1,DIV,1,SECTION,0,H3",
            "selector": "div.grid-container > div > section > h3",
            "boundingRect": {
              "top": 548,
              "bottom": 584,
              "left": 451,
              "right": 1091,
              "width": 640,
              "height": 36
            },
            "snippet": "<h3 data-bind=\"visible: searchableTags().length >",
            "nodeLabel": "Categories",
            "explanation": "Fix any of the following:\n  Heading order invalid"
          }
        }
      ],
      "debugData": {
        "type": "debugdata",
        "impact": "moderate",
        "tags": [
          "cat.semantics",
          "best-practice"
        ]
      }
    },
    "errorCount": 1
  },
  {
    "id": "link-name",
    "title": "Links do not have a discernible name",
    "description": "Link text (and alternate text for images, when used as links) that is discernible, unique, and focusable improves the navigation experience for screen reader users. [Learn more](https://web.dev/link-name/).",
    "score": 0,
    "scoreDisplayMode": "binary",
    "details": {
      "type": "table",
      "headings": [
        {
          "key": "node",
          "itemType": "node",
          "subItemsHeading": {
            "key": "relatedNode",
            "itemType": "node"
          },
          "text": "Failing Elements"
        }
      ],
      "items": [
        {
          "node": {
            "type": "node",
            "lhId": "9-247-A",
            "path": "1,HTML,1,BODY,10,MAIN,1,DIV,0,DIV,1,DIV,0,DIV,1,DIV,0,NAV,1,UL,9,LI,0,A",
            "selector": "nav#SideNav > ul#SecondaryNavigation > li.usa-sidenav__item > a",
            "boundingRect": {
              "top": 679,
              "bottom": 695,
              "left": 195,
              "right": 371,
              "width": 176,
              "height": 16
            },
            "snippet": "<a href=\"/frequently-asked-questions/federal-academic-alliance-faqs/\" class=\"\">",
            "nodeLabel": "nav#SideNav > ul#SecondaryNavigation > li.usa-sidenav__item > a",
            "explanation": "Fix all of the following:\n  Element is in tab order and does not have accessible text\n\nFix any of the following:\n  Element does not have text that is visible to screen readers\n  aria-label attribute does not exist or is empty\n  aria-labelledby attribute does not exist, references elements that do not exist or references elements that are empty\n  Element has no title attribute"
          }
        }
      ],
      "debugData": {
        "type": "debugdata",
        "impact": "serious",
        "tags": [
          "cat.name-role-value",
          "wcag2a",
          "wcag412",
          "wcag244",
          "section508",
          "section508.22.a",
          "ACT"
        ]
      }
    },
    "errorCount": 1
  }
]